posydon/__init__.py
posydon/_version.py
posydon/mymodule/__init__.py
posydon/mymodule/mymodule.py
posydon-0.0.1b0.dist-info/LICENSE
posydon-0.0.1b0.dist-info/METADATA
posydon-0.0.1b0.dist-info/WHEEL
posydon-0.0.1b0.dist-info/top_level.txt
posydon-0.0.1b0.dist-info/RECORD
