Metadata-Version: 2.1
Name: posydon
Version: 0.0.1b0
Summary: POSYDON Stellar Evolution Package
Home-page: https://github.com/POSYDON-code/POSYDON
Author: POSYDON Collaboration
Author-email: scottcoughlin2014@u.northwestern.edu
License: GPLv3+
Platform: UNKNOWN
Classifier: Development Status :: 4 - Beta
Classifier: Programming Language :: Python
Classifier: Programming Language :: Python :: 3.6
Classifier: Programming Language :: Python :: 3.7
Classifier: Programming Language :: Python :: 3.8
Classifier: Intended Audience :: Science/Research
Classifier: Intended Audience :: End Users/Desktop
Classifier: Intended Audience :: Science/Research
Classifier: Natural Language :: English
Classifier: Topic :: Scientific/Engineering
Classifier: Topic :: Scientific/Engineering :: Astronomy
Classifier: Topic :: Scientific/Engineering :: Physics
Classifier: Operating System :: POSIX
Classifier: Operating System :: Unix
Classifier: Operating System :: MacOS
Classifier: License :: OSI Approved :: GNU General Public License v3 or later (GPLv3+)
Provides: posydon
Requires-Python: >3.5
Requires-Dist: numpy (>=1.16)
Provides-Extra: doc
Requires-Dist: matplotlib ; extra == 'doc'
Requires-Dist: ipython ; extra == 'doc'
Requires-Dist: sphinx ; extra == 'doc'
Requires-Dist: numpydoc ; extra == 'doc'
Requires-Dist: sphinx-rtd-theme ; extra == 'doc'
Requires-Dist: sphinxcontrib-programoutput ; extra == 'doc'
Provides-Extra: ml
Requires-Dist: theano ; extra == 'ml'
